odoo9_addon_runbot_build_instructions-9.0.1.0.0-py2.7-nspkg.pth
odoo9_addon_runbot_build_instructions-9.0.1.0.0.dist-info/top_level.txt
odoo9_addon_runbot_build_instructions-9.0.1.0.0.dist-info/WHEEL
odoo9_addon_runbot_build_instructions-9.0.1.0.0.dist-info/RECORD
odoo9_addon_runbot_build_instructions-9.0.1.0.0.dist-info/metadata.json
odoo9_addon_runbot_build_instructions-9.0.1.0.0.dist-info/DESCRIPTION.rst
odoo9_addon_runbot_build_instructions-9.0.1.0.0.dist-info/METADATA
odoo9_addon_runbot_build_instructions-9.0.1.0.0.dist-info/namespace_packages.txt
odoo_addons/runbot_build_instructions/__openerp__.py
odoo_addons/runbot_build_instructions/__init__.py
odoo_addons/runbot_build_instructions/README.rst
odoo_addons/runbot_build_instructions/models/runbot_build.py
odoo_addons/runbot_build_instructions/models/__init__.py
odoo_addons/runbot_build_instructions/models/runbot_repo.py
odoo_addons/runbot_build_instructions/views/runbot_repo.xml
